py_kvstore/__init__.py
py_kvstore/py_kvstore.py
py_kvstore/test.py
py_kvstore-0.0.7.dist-info/METADATA
py_kvstore-0.0.7.dist-info/WHEEL
py_kvstore-0.0.7.dist-info/top_level.txt
py_kvstore-0.0.7.dist-info/RECORD
