Metadata-Version: 2.1
Name: py-kvstore
Version: 0.0.7
Summary: A key value store
Home-page: https://github.com/Reecepbcups/py_kvstore
Author: Reece Willims
Author-email: reecepbcups@gmail.com
License: Apache 2.0
Classifier: Development Status :: 1 - Planning
Classifier: Intended Audience :: Science/Research
Classifier: License :: OSI Approved :: BSD License
Classifier: Operating System :: POSIX :: Linux
Classifier: Programming Language :: Python :: 3
Classifier: Programming Language :: Python :: 3.8
Classifier: Programming Language :: Python :: 3.9
Classifier: Programming Language :: Python :: 3.10
